borgitory/__init__.py
borgitory/alembic.ini
borgitory/cli.py
borgitory/config_module.py
borgitory/custom_types.py
borgitory/dependencies.py
borgitory/main.py
borgitory/py.typed
borgitory/alembic/README
borgitory/alembic/env.py
borgitory/alembic/script.py.mako
borgitory/alembic/versions/02b7b29d38c0_add_encryption_type_and_keyfile_content_.py
borgitory/alembic/versions/18b9095bc772_add_patterns_column_to_schedules_table.py
borgitory/alembic/versions/1d47e9231dd0_rename_cleanup_to_prune.py
borgitory/alembic/versions/3335c0eac68e_create_initial_schema.py
borgitory/alembic/versions/5e6cc17d11a5_user_installed_packages.py
borgitory/alembic/versions/9b5d5f5e8cbc_add_pre_post_job_hooks_to_schedule.py
borgitory/alembic/versions/9e4c8456ea53_add_cache_dir_field_to_repositories_.py
borgitory/alembic/versions/9f06f8c8088d_initial_empty_state.py
borgitory/alembic/versions/eb3518e71c73_add_more_prune_settings_to_cleanup_.py
borgitory/api/__init__.py
borgitory/api/auth.py
borgitory/api/backups.py
borgitory/api/cancel_on_disconnect.py
borgitory/api/cloud_sync.py
borgitory/api/debug.py
borgitory/api/jobs.py
borgitory/api/notifications.py
borgitory/api/packages.py
borgitory/api/prune.py
borgitory/api/repositories.py
borgitory/api/repository_check_configs.py
borgitory/api/repository_stats.py
borgitory/api/schedules.py
borgitory/api/shared.py
borgitory/api/tabs.py
borgitory/config/__init__.py
borgitory/config/command_runner_config.py
borgitory/config/job_manager_config.py
borgitory/constants/__init__.py
borgitory/constants/retention.py
borgitory/factories/__init__.py
borgitory/factories/service_factory.py
borgitory/models/__init__.py
borgitory/models/borg_info.py
borgitory/models/database.py
borgitory/models/enums.py
borgitory/models/job_results.py
borgitory/models/patterns.py
borgitory/models/repository_dtos.py
borgitory/models/schemas.py
borgitory/protocols/__init__.py
borgitory/protocols/archive_manager_protocol.py
borgitory/protocols/cloud_protocols.py
borgitory-2.5.5.dist-info/METADATA
borgitory-2.5.5.dist-info/WHEEL
borgitory-2.5.5.dist-info/entry_points.txt
borgitory-2.5.5.dist-info/licenses/LICENSE
borgitory-2.5.5.dist-info/RECORD
