Metadata-Version: 2.4
Name: borgitory
Version: 2.5.5
Summary: A comprehensive web-based management interface for BorgBackup repositories with real-time monitoring, automated scheduling, and cloud synchronization capabilities.
Project-URL: Homepage, https://github.com/mlapaglia/Borgitory
Project-URL: Repository, https://github.com/mlapaglia/Borgitory
Project-URL: Issues, https://github.com/mlapaglia/Borgitory/issues
Author-email: mlapaglia <mlapaglia@users.noreply.github.com>
License: MIT License
License-File: LICENSE
Keywords: archive-management,backup,borgbackup,cloud-sync,scheduling,web-interface
Classifier: Development Status :: 4 - Beta
Classifier: Intended Audience :: System Administrators
Classifier: License :: OSI Approved :: MIT License
Classifier: Operating System :: OS Independent
Classifier: Programming Language :: Python :: 3
Classifier: Programming Language :: Python :: 3.13
Classifier: Topic :: System :: Archiving :: Backup
Classifier: Topic :: System :: Systems Administration
Requires-Python: >=3.13
Requires-Dist: aiofiles>=24.1.0
Requires-Dist: aiohttp>=3.9.0
Requires-Dist: alembic>=1.16.5
Requires-Dist: apscheduler>=3.10.4
Requires-Dist: bcrypt<5.0.0,>=4.0.0
Requires-Dist: cron-descriptor>=2.0.5
Requires-Dist: cryptography>=45.0.0
Requires-Dist: docker>=7.1.0
Requires-Dist: fastapi>=0.115.0
Requires-Dist: jinja2>=3.1.4
Requires-Dist: passlib[bcrypt]>=1.7.4
Requires-Dist: pydantic>=2.9.0
Requires-Dist: python-dotenv>=1.0.1
Requires-Dist: python-multipart>=0.0.12
Requires-Dist: sqlalchemy>=2.0.35
Requires-Dist: sse-starlette>=2.1.3
Requires-Dist: uvicorn[standard]>=0.30.0
Provides-Extra: dev
Requires-Dist: debugpy>=1.8.17; extra == 'dev'
Requires-Dist: httpx>=0.25.0; extra == 'dev'
Requires-Dist: mypy>=1.8.0; extra == 'dev'
Requires-Dist: pytest-asyncio>=0.21.0; extra == 'dev'
Requires-Dist: pytest-cov>=4.0.0; extra == 'dev'
Requires-Dist: pytest>=7.4.0; extra == 'dev'
Requires-Dist: ruff>=0.12.11; extra == 'dev'
Requires-Dist: sqlalchemy[mypy]>=2.0.35; extra == 'dev'
Requires-Dist: types-aiofiles>=23.2.0.20240106; extra == 'dev'
Requires-Dist: types-passlib>=1.7.7.20240327; extra == 'dev'
Requires-Dist: types-python-dateutil>=2.8.19.20240106; extra == 'dev'
